mysql_to_sqlite3/__init__.py
mysql_to_sqlite3/cli.py
mysql_to_sqlite3/click_utils.py
mysql_to_sqlite3/debug_info.py
mysql_to_sqlite3/mysql_utils.py
mysql_to_sqlite3/py.typed
mysql_to_sqlite3/sqlite_utils.py
mysql_to_sqlite3/transporter.py
mysql_to_sqlite3/types.py
mysql_to_sqlite3-2.5.2.dist-info/METADATA
mysql_to_sqlite3-2.5.2.dist-info/WHEEL
mysql_to_sqlite3-2.5.2.dist-info/entry_points.txt
mysql_to_sqlite3-2.5.2.dist-info/licenses/LICENSE
mysql_to_sqlite3-2.5.2.dist-info/RECORD
