Metadata-Version: 2.4
Name: mysql-to-sqlite3
Version: 2.5.2
Summary: A simple Python tool to transfer data from MySQL to SQLite 3
Project-URL: Homepage, https://techouse.github.io/mysql-to-sqlite3/
Project-URL: Documentation, https://techouse.github.io/mysql-to-sqlite3/
Project-URL: Repository, https://github.com/techouse/mysql-to-sqlite3.git
Project-URL: Issues, https://github.com/techouse/mysql-to-sqlite3
Project-URL: Changelog, https://github.com/techouse/mysql-to-sqlite3/blob/master/CHANGELOG.md
Project-URL: Sponsor, https://github.com/sponsors/techouse
Project-URL: PayPal, https://paypal.me/ktusar
Author-email: Klemen Tusar <techouse@gmail.com>
License-Expression: MIT
License-File: LICENSE
Keywords: data,migrate,migration,mysql,sqlite3,transfer
Classifier: Development Status :: 5 - Production/Stable
Classifier: Environment :: Console
Classifier: Intended Audience :: Developers
Classifier: Intended Audience :: End Users/Desktop
Classifier: Intended Audience :: System Administrators
Classifier: License :: OSI Approved :: MIT License
Classifier: Operating System :: OS Independent
Classifier: Programming Language :: Python
Classifier: Programming Language :: Python :: 3
Classifier: Programming Language :: Python :: 3.9
Classifier: Programming Language :: Python :: 3.10
Classifier: Programming Language :: Python :: 3.11
Classifier: Programming Language :: Python :: 3.12
Classifier: Programming Language :: Python :: 3.13
Classifier: Programming Language :: Python :: Implementation :: CPython
Classifier: Topic :: Database
Classifier: Typing :: Typed
Requires-Python: >=3.9
Requires-Dist: click>=8.1.3
Requires-Dist: mysql-connector-python>=9.0.0
Requires-Dist: python-dateutil>=2.9.0.post0
Requires-Dist: python-slugify>=7.0.0
Requires-Dist: pytimeparse2
Requires-Dist: simplejson>=3.19.0
Requires-Dist: sqlglot>=27.27.0
Requires-Dist: tabulate
Requires-Dist: tqdm>=4.65.0
Requires-Dist: typing-extensions; python_version < '3.11'
Provides-Extra: dev
Requires-Dist: docker>=6.1.3; extra == 'dev'
Requires-Dist: factory-boy; extra == 'dev'
Requires-Dist: faker>=18.10.0; extra == 'dev'
Requires-Dist: mypy>=1.3.0; extra == 'dev'
Requires-Dist: mysqlclient>=2.1.1; extra == 'dev'
Requires-Dist: packaging; extra == 'dev'
Requires-Dist: pytest-cov; extra == 'dev'
Requires-Dist: pytest-mock; extra == 'dev'
Requires-Dist: pytest-timeout; extra == 'dev'
Requires-Dist: pytest>=7.3.1; extra == 'dev'
Requires-Dist: requests; extra == 'dev'
Requires-Dist: sqlalchemy-utils; extra == 'dev'
Requires-Dist: sqlalchemy>=2.0.0; extra == 'dev'
Requires-Dist: tox; extra == 'dev'
Requires-Dist: types-python-dateutil; extra == 'dev'
Requires-Dist: types-python-slugify; extra == 'dev'
Requires-Dist: types-requests; extra == 'dev'
Requires-Dist: types-simplejson; extra == 'dev'
Requires-Dist: types-sqlalchemy-utils; extra == 'dev'
Requires-Dist: types-tabulate; extra == 'dev'
Requires-Dist: types-tqdm; extra == 'dev'
